importlite/__init__.py
importlite/__main__.py
importlite/csv_util.py
importlite/dbwrappers.py
importlite/schema.py
importlite/sqlgen.py
importlite-0.1.0.dist-info/DESCRIPTION.rst
importlite-0.1.0.dist-info/METADATA
importlite-0.1.0.dist-info/RECORD
importlite-0.1.0.dist-info/WHEEL
importlite-0.1.0.dist-info/entry_points.txt
importlite-0.1.0.dist-info/metadata.json
importlite-0.1.0.dist-info/top_level.txt
