Metadata-Version: 2.0
Name: importlite
Version: 0.1.0
Summary: Import CSV files into SQLite databases
Home-page: https://github.com/KatrinaE/importlite
Author: Katrina Ellison Geltman
Author-email: katrina.m.ellison@gmail.com
License: MIT
Keywords: csv sqlite
Platform: UNKNOWN
Classifier: Development Status :: 3 - Alpha
Classifier: Intended Audience :: Developers
Classifier: Topic :: Database
Classifier: License :: OSI Approved :: MIT License
Classifier: Programming Language :: Python :: 2.7
Classifier: Programming Language :: Python :: 3.2
Classifier: Programming Language :: Python :: 3.3
Classifier: Programming Language :: Python :: 3.4
Classifier: Programming Language :: Python :: 3.5
